karton_config_extractor-2.2.0-nspkg.pth
karton/config_extractor/__init__.py
karton/config_extractor/__main__.py
karton/config_extractor/__version__.py
karton/config_extractor/config_extractor.py
karton/config_extractor/util.py
karton_config_extractor-2.2.0.dist-info/LICENSE
karton_config_extractor-2.2.0.dist-info/METADATA
karton_config_extractor-2.2.0.dist-info/WHEEL
karton_config_extractor-2.2.0.dist-info/entry_points.txt
karton_config_extractor-2.2.0.dist-info/namespace_packages.txt
karton_config_extractor-2.2.0.dist-info/top_level.txt
karton_config_extractor-2.2.0.dist-info/RECORD
