Metadata-Version: 2.1
Name: karton-config-extractor
Version: 2.2.0
Summary: Static configuration extractor for the Karton framework
Home-page: https://github.com/CERT-Polska/karton-config-extractor
License: UNKNOWN
Platform: UNKNOWN
Classifier: Programming Language :: Python
Classifier: Operating System :: OS Independent
License-File: LICENSE
Requires-Dist: karton-core (<6.0.0,>=5.0.0)
Requires-Dist: malduck (<5.0.0,>=4.2.0)
